tlgcp/__init__.py
tlgcp/data/__init__.py
tlgcp/data/rainfall_india.csv
tlgcp/data/tensor_dataset.py
tlgcp/data/test/__init__.py
tlgcp/data/test/test_tensor_dataset.py
tlgcp/generalized_parafac/__init__.py
tlgcp/generalized_parafac/_generalized_parafac.py
tlgcp/generalized_parafac/_stochastic_generalized_parafac.py
tlgcp/generalized_parafac/tests/__init__.py
tlgcp/generalized_parafac/tests/test_generalized_parafac.py
tlgcp/generalized_parafac/tests/test_stochastic_generalized_parafac.py
tlgcp/utils/__init__.py
tlgcp/utils/_lbfgs.py
tlgcp/utils/losses_and_gradients.py
tlgcp/utils/tests/__init__.py
tlgcp/utils/tests/test_lbfgs.py
tlgcp/utils/tests/test_losses_and_gradients.py
tensorly_gcp-0.1.0.dist-info/LICENSE.txt
tensorly_gcp-0.1.0.dist-info/METADATA
tensorly_gcp-0.1.0.dist-info/WHEEL
tensorly_gcp-0.1.0.dist-info/top_level.txt
tensorly_gcp-0.1.0.dist-info/RECORD
