Metadata-Version: 2.1
Name: tensorly-gcp
Version: 0.1.0
Summary: Generalized CP Decomposition with Tensorly
Home-page: UNKNOWN
Author: Caglayan Tuna
Author-email: caglayantun@gmail.com
License: Modified BSD
Platform: UNKNOWN
Classifier: Topic :: Scientific/Engineering
Classifier: License :: OSI Approved :: BSD License
Classifier: Programming Language :: Python :: 3
License-File: LICENSE.txt
Requires-Dist: numpy
Requires-Dist: scipy
Requires-Dist: tensorly
